ensembler/__init__.py
ensembler/dataset.py
ensembler/ensembler.py
ensembler/job.py
ensembler/sink.py
ensembler/source.py
tests/__init__.py
tests/conftest.py
tests/dataset_test.py
tests/ensembler_test.py
tests/sink_test.py
tests/utils/__init__.py
tests/utils/openapi_utils.py
naufal_pyfunc_ensembler_job-0.0.0.dist-info/METADATA
naufal_pyfunc_ensembler_job-0.0.0.dist-info/WHEEL
naufal_pyfunc_ensembler_job-0.0.0.dist-info/top_level.txt
naufal_pyfunc_ensembler_job-0.0.0.dist-info/RECORD
